fulladder/fulladder.v
module fulladder(a,b,c,carry,sum);

input a,b,c;
output carry,sum;
xor x1(d,a,b);
xor x2(carry,d,c);
and a2(f,d,c);
and a1(e,a,b);
or o1(sum,e,f);
endmodule

fulladder/fulladder_tb.v
`include "fulladder.v"
module fulladder_tb;

reg a,b,c;
wire d,e,f,sum,carry;
fulladder f1(a,b,c,carry,sum);
initial begin
  $dumpfile("fulladder.vcd");
  $dumpvars(0,fulladder_tb);

  a=0;b=0;c=0;
  #10

  a=0;b=0;c=1;
  #10

  a=0;b=1;c=0;
  #10

  a=0;b=1;c=1;
  #10

  a=1;b=0;c=0;
  #10

  a=1;b=0;c=1;
  #10

  a=1;b=1;c=0;
  #10

  a=1;b=1;c=1;
  #10
  $finish;
end
endmodule

fulladder/fulladder.vcd
$date
	Sat Jun 17 05:17:49 2023
$end
$version
	Icarus Verilog
$end
$timescale
	1s
$end
$scope module fulladder_tb $end
$var wire 1 ! sum $end
$var wire 1 " carry $end
$var reg 1 # a $end
$var reg 1 $ b $end
$var reg 1 % c $end
$scope module f1 $end
$var wire 1 # a $end
$var wire 1 $ b $end
$var wire 1 % c $end
$var wire 1 " carry $end
$var wire 1 & d $end
$var wire 1 ' e $end
$var wire 1 ( f $end
$var wire 1 ! sum $end
$upscope $end
$upscope $end
$enddefinitions $end
$comment Show the parameter values. $end
$dumpall
$end
#0
$dumpvars
0(
0'
0&
0%
0$
0#
0"
0!
$end
#10
1"
1%
#20
1&
0%
1$
#30
1!
0"
1(
1%
#40
0!
1"
0(
0%
0$
1#
#50
1!
0"
1(
1%
#60
0(
0&
1'
0%
1$
#70
1"
1%
