decoder/decode.v
module decode(a0,a1,a2,y);

input a0,a1,a2;
output [7:0]y;
//output y0,y1,y2,y3,y4,y5,y6,y7;
//output y0,y1,y2,y3;

assign y[0] = ~a0 & ~a1 & ~ a2;
assign y[1] = ~a0 & ~a1 &  a2;
assign y[2] = ~a0 & a1 & ~ a2;
assign y[3] = ~a0 & a1 &  a2;
assign y[4] = a0 & ~a1 & ~ a2;
assign y[5] = a0 & ~a1 &  a2;
assign y[6] = a0 & a1 & ~ a2;
assign y[7] = a0 & a1 &  a2;
endmodule

decoder/decode_tb.v
`include "decode.v"
module decode_tb;

reg a0,a1,a2;
wire [7:0]y;

decode d1(a0,a1,a2,y);

initial begin
    $dumpfile("decode.vcd");
    $dumpvars(0,decode_tb);

   a0=0;a1=0;a2=0;
   #8 $stop;
end

always #4 a0=~a0;
always #2 a1=~a1;
always #1 a2=~a2;

endmodule

decoder/decode.vcd
$date
	Thu Jul 06 12:11:28 2023
$end
$version
	Icarus Verilog
$end
$timescale
	1s
$end
$scope module decode_tb $end
$var wire 8 ! y [7:0] $end
$var reg 1 " a0 $end
$var reg 1 # a1 $end
$var reg 1 $ a2 $end
$scope module d1 $end
$var wire 1 " a0 $end
$var wire 1 # a1 $end
$var wire 1 $ a2 $end
$var wire 8 % y [7:0] $end
$upscope $end
$upscope $end
$enddefinitions $end
$comment Show the parameter values. $end
$dumpall
$end
#0
$dumpvars
b1 %
0$
0#
0"
b1 !
$end
#1
b10 !
b10 %
1$
#2
b100 !
b100 %
0$
1#
#3
b1000 !
b1000 %
1$
#4
b10000 !
b10000 %
0$
0#
1"
#5
b100000 !
b100000 %
1$
#6
b1000000 !
b1000000 %
0$
1#
#7
b10000000 !
b10000000 %
1$
